[{"n":"RUSSOTTO, VINCENT PAUL","b":"","a":"10 RALPH DR","c":"FAIRFIELD","s":"NJ","z":"07004","p":"9084007480","t":"01","lat":40.8822,"lng":-74.296},{"n":"SIMPLE TRADE LLC","b":"","a":"7 SPIELMAN RD","c":"FAIRFIELD","s":"NJ","z":"07004","p":"9739805268","t":"01","lat":40.8822,"lng":-74.296},{"n":"PINE TAM LLC","b":"","a":"1 BALDWIN CT","c":"FAIRFIELD","s":"NJ","z":"07004","p":"9737676620","t":"01","lat":40.8822,"lng":-74.296},{"n":"BOYKO, JOHN JR","b":"","a":"60 JEFFERSON ST","c":"CLIFTON","s":"NJ","z":"07014","p":"9734730807","t":"01","lat":40.8344,"lng":-74.1377},{"n":"ASSADOURIAN ARMS INC","b":"MIKES\u0027S GUN SHOP","a":"355 ANDERSON AVE","c":"FAIRVIEW","s":"NJ","z":"07022","p":"2019415661","t":"01","lat":40.817,"lng":-74},{"n":"CROWN GLOBAL ENTERPRISES LLC","b":"G3 UNLIMITED","a":"357 MIDLAND AVENUE","c":"GARFIELD","s":"NJ","z":"07026","p":"5514867404","t":"01","lat":40.8789,"lng":-74.1081},{"n":"CROWN GLOBAL ENTERPRISES LLC","b":"G3 UNLIMITED","a":"357 MIDLAND AVENUE","c":"GARFIELD","s":"NJ","z":"07026","p":"9085461563","t":"07","lat":40.8789,"lng":-74.1081},{"n":"BOLCAR, KEVIN","b":"","a":"186 HARTMANN AVE","c":"GARFIELD","s":"NJ","z":"07026","p":"9732297493","t":"01","lat":40.8789,"lng":-74.1081},{"n":"SPECTRE FIREARMS LLC","b":"","a":"502 SPRUCE AVE","c":"GARWOOD","s":"NJ","z":"07027","p":"9086126044","t":"01","lat":40.6512,"lng":-74.3239},{"n":"MJFW LLC","b":"SHOT CALLERS FIREARMS","a":"20 NOEL DRIVE","c":"NORTH ARLINGTON","s":"NJ","z":"07031","p":"2016001558","t":"07","lat":40.7898,"lng":-74.1343},{"n":"MJF LLC","b":"EXCLUSIVE ARMS","a":"20 NOEL DRIVE","c":"NORTH ARLINGTON","s":"NJ","z":"07031","p":"2016001558","t":"07","lat":40.7898,"lng":-74.1343},{"n":"THE OPERATOR\u0027S CORNER LLC","b":"","a":"98 ALGONQUIN AVE","c":"LINCOLN PARK","s":"NJ","z":"07035","p":"9739548168","t":"01","lat":40.9208,"lng":-74.2995},{"n":"SAVANNAHARRISON HARDWARE LLC","b":"LINCOLN PARK TRUE VALUE HARDWARE","a":"206 MAIN ST","c":"LINCOLN PARK","s":"NJ","z":"07035","p":"8622210528","t":"01","lat":40.9208,"lng":-74.2995},{"n":"SMOKIN GUNS TACTICAL SOLUTIONS LLC","b":"","a":"240 W LINDEN AVE","c":"LINDEN","s":"NJ","z":"07036","p":"9085789730","t":"01","lat":40.6354,"lng":-74.2556},{"n":"JH CRIMINALISTICS, LLC","b":"","a":"29 PLYMOUTH AVE","c":"MAPLEWOOD","s":"NJ","z":"07040","p":"6462283201","t":"01","lat":40.7279,"lng":-74.2656},{"n":"FSS ARMORY INC","b":"","a":"36 RT 46","c":"PINEBROOK","s":"NJ","z":"07058","p":"9735150911","t":"07","lat":40.8742,"lng":-74.35},{"n":"NEW CASTLE WEST INVESTMENTS LLC","b":"GARDEN STATE ARMORY","a":"165 WASHINGTON VALLEY ROAD SUITE #2A","c":"WARREN","s":"NJ","z":"07059","p":"7328938500","t":"01","lat":40.6318,"lng":-74.5105},{"n":"HERITAGE GUILD OF RARITAN BAY LLC","b":"","a":"344 ST GEORGES AVE","c":"RAHWAY","s":"NJ","z":"07065","p":"7323824066","t":"01","lat":40.6087,"lng":-74.2819},{"n":"JJ \u0026 DK SPORT SHOP INC","b":"J DEPAZZA GUNSMITH","a":"344 ST GEORGES AVE","c":"RAHWAY","s":"NJ","z":"07065","p":"7323810698","t":"07","lat":40.6087,"lng":-74.2819},{"n":"UNITED MARINE SECURITY, LLC","b":"","a":"117 HARRISON AVENUE BUILDING #2","c":"ROSELAND","s":"NJ","z":"07068","p":"2013018840","t":"08","lat":40.8203,"lng":-74.3047},{"n":"ENDGAME TECHNOLOGY LLC","b":"ZEROMARK","a":"65 VAIL LANE","c":"WATCHUNG","s":"NJ","z":"07069","p":"9416505395","t":"07","lat":40.6378,"lng":-74.4514},{"n":"LAHULLIER, CRAIG JOHN","b":"CRAIGS FIREARMS","a":"325 MAIN ST","c":"EAST RUTHERFORD","s":"NJ","z":"07073","p":"2014601430","t":"01","lat":40.8385,"lng":-74.1041},{"n":"A-ZONE TACTICAL LLC","b":"","a":"1206 RONY ROAD","c":"UNION","s":"NJ","z":"07083","p":"9737718111","t":"01","lat":40.6952,"lng":-74.2677},{"n":"RTSP UNION, LLC","b":"","a":"2438 US HIGHWAY 22 EAST","c":"UNION","s":"NJ","z":"07083","p":"9734347600","t":"07","lat":40.6952,"lng":-74.2677},{"n":"DECECCO, LUIGI","b":"LOUIE GS OUTDOORS","a":"829 9TH ST","c":"SECAUCUS","s":"NJ","z":"07094","p":"2014814367","t":"01","lat":40.791,"lng":-74.0634},{"n":"DECECCO, LUIGI","b":"LOUIE G\u0027S OUTDOORS","a":"829 9TH ST","c":"SECAUCUS","s":"NJ","z":"07094","p":"2014814367","t":"07","lat":40.791,"lng":-74.0634},{"n":"LONG SHOT PISTOL AND RIFLE, LLC","b":"","a":"375 COUNTY AVENUE SUITE 1","c":"SECAUCUS","s":"NJ","z":"07094","p":"2017351875","t":"07","lat":40.791,"lng":-74.0634},{"n":"LONG SHOT PISTOL AND RIFLE, LLC","b":"","a":"375 COUNTY AVE SUITE 1","c":"SECAUCUS","s":"NJ","z":"07094","p":"2017351875","t":"08","lat":40.791,"lng":-74.0634},{"n":"BULLSEYE TACTICAL SUPPLY, INC","b":"","a":"114 CD MAIN STREET","c":"WOODBRIDGE","s":"NJ","z":"07095","p":"7322188415","t":"07","lat":40.556,"lng":-74.2845},{"n":"BULLSEYE TACTICAL SUPPLY, INC","b":"","a":"114 CD MAIN STREET","c":"WOODBRIDGE","s":"NJ","z":"07095","p":"7322188415","t":"08","lat":40.556,"lng":-74.2845},{"n":"BULLET HOLE, INC","b":"","a":"78 RUTGERS ST","c":"BELLEVILLE","s":"NJ","z":"07109","p":"9737593968","t":"01","lat":40.7946,"lng":-74.1631},{"n":"H \u0026 A PRODUCT INC","b":"SKY TACTICAL","a":"1131 BANK STREET","c":"HILLSIDE","s":"NJ","z":"07205","p":"8452170096","t":"01","lat":40.6968,"lng":-74.2281},{"n":"SAK ARMS LLC","b":"","a":"1021 JOHN GLENN DRIVE","c":"HILLSIDE","s":"NJ","z":"07205","p":"9087505085","t":"07","lat":40.6968,"lng":-74.2281},{"n":"URBAN TACTICAL LLC","b":"","a":"548 WEST SIDE AVENUE","c":"JERSEY CITY","s":"NJ","z":"07304","p":"2014993601","t":"01","lat":40.718,"lng":-74.0754},{"n":"JIMMY CANNON LLC","b":"","a":"174 DANFORTH AVE","c":"JERSEY CITY","s":"NJ","z":"07305","p":"2013869451","t":"01","lat":40.702,"lng":-74.089},{"n":"DAVIS, DARNELL ANTHONY","b":"","a":"146 OCEAN AVE","c":"JERSEY CITY","s":"NJ","z":"07305","p":"9737574506","t":"01","lat":40.702,"lng":-74.089},{"n":"CASOS GUN-A-RAMA INC","b":"","a":"176 DANFORTH AVE","c":"JERSEY CITY","s":"NJ","z":"07305","p":"2014355099","t":"01","lat":40.702,"lng":-74.089},{"n":"SCHARFF, WILLIAM JAMES","b":"","a":"39 E CRESCENT AVE","c":"ALLENDALE","s":"NJ","z":"07401","p":"2016382051","t":"01","lat":41.0327,"lng":-74.1342},{"n":"PCDC ENTERPRISES, LLC","b":"3 C GUNSMITHING    3 C GUNS","a":"314 UNION AVENUE","c":"BLOOMINGDALE","s":"NJ","z":"07403","p":"2016973543","t":"07","lat":41.0128,"lng":-74.3338},{"n":"2A GUN SHOP LLC","b":"","a":"21 MAIN STREET","c":"BUTLER","s":"NJ","z":"07405","p":"9736009694","t":"07","lat":40.9988,"lng":-74.4261},{"n":"HIGGINS ARMS LLC","b":"","a":"9 COUNTRY LANE","c":"HAMBURG","s":"NJ","z":"07419","p":"8623542588","t":"01","lat":41.1467,"lng":-74.5874},{"n":"MASTODON AMMO \u0026 CAMO LLC","b":"","a":"195 HIGHLAND LAKES RD","c":"HIGHLAND LAKES","s":"NJ","z":"07422","p":"9737649550","t":"07","lat":41.1826,"lng":-74.4564},{"n":"WOODLAND PARK RANGE II, LLC","b":"GUN FOR HIRE","a":"1267 MCBRIDE AVE","c":"WOODLAND PARK","s":"NJ","z":"07424","p":"8884863674","t":"07","lat":40.8835,"lng":-74.2144},{"n":"SIX SHOOTER SUPPLY LLC","b":"","a":"286 VREELAND AVE","c":"MIDLAND PARK","s":"NJ","z":"07432","p":"2015661335","t":"07","lat":40.9957,"lng":-74.1409},{"n":"MICRON MACHINE IND INC","b":"","a":"27 UNION VALLEY RD","c":"NEWFOUNDLAND","s":"NJ","z":"07435","p":"9736972624","t":"01","lat":41.0647,"lng":-74.4359},{"n":"SPEED SHOP TACTICAL LLC","b":"","a":"2915 RT 23, UNIT #4","c":"NEWFOUNDLAND","s":"NJ","z":"07435","p":"9734094121","t":"07","lat":41.0647,"lng":-74.4359},{"n":"FIMS FIREARMS, INC","b":"FIMS FIREARMS","a":"8 ALLERMAN ROAD","c":"OAKLAND","s":"NJ","z":"07436","p":"2018457088","t":"07","lat":41.0294,"lng":-74.2338},{"n":"OAK RIDGE FIREARMS LLC","b":"","a":"3050 ROUTE 23","c":"OAK RIDGE","s":"NJ","z":"07438","p":"9734094631","t":"01","lat":41.0302,"lng":-74.5198},{"n":"BRYAN\u0027S GUNS LLC","b":"","a":"5415 BERKSHIRE VALLEY RD","c":"OAK RIDGE","s":"NJ","z":"07438","p":"9732196304","t":"01","lat":41.0302,"lng":-74.5198},{"n":"SHUFLAT, MICHAEL","b":"SHUFLATS ORDINANCE \u0026 REPAIR","a":"150 BROOKS FLAT RD","c":"OGDENSBURG","s":"NJ","z":"07439","p":"9736702815","t":"01","lat":41.0767,"lng":-74.5982},{"n":"THE SPY SITE STORE CORP","b":"","a":"410 ROUTE 23 NORTH","c":"POMPTON PLAINS","s":"NJ","z":"07444","p":"8453710000","t":"01","lat":40.9655,"lng":-74.3016},{"n":"LIBERTY SALES \u0026 TRANSFER LLC","b":"","a":"37 B SWAN ST","c":"RAMSEY","s":"NJ","z":"07446","p":"2019547781","t":"01","lat":41.0577,"lng":-74.1445},{"n":"RAMSEY OUTDOOR STORE, INC","b":"","a":"835 ROUTE 17 SOUTH","c":"RAMSEY","s":"NJ","z":"07446","p":"2013278141","t":"07","lat":41.0577,"lng":-74.1445},{"n":"RAMSEY OUTDOOR STORE INC","b":"","a":"835 RT 17","c":"RAMSEY","s":"NJ","z":"07446","p":"2013278141","t":"01","lat":41.0577,"lng":-74.1445},{"n":"TRIPLE C ENTERPRISES LLC","b":"LIBERTY SPORTING ARMS","a":"10 LIBERTY STREET","c":"RIDGEWOOD","s":"NJ","z":"07450","p":"5512388499","t":"01","lat":40.982,"lng":-74.1131},{"n":"LEGACY ARMS LLC","b":"","a":"898 HAMMOND RD","c":"RIDGEWOOD","s":"NJ","z":"07450","p":"2015275257","t":"07","lat":40.982,"lng":-74.1131},{"n":"TARGET SPORTS INC","b":"THUNDER MOUNTAIN TRAP AND SKEET","a":"1 MANSION DR","c":"RINGWOOD","s":"NJ","z":"07456","p":"9739626377","t":"01","lat":41.0928,"lng":-74.2659},{"n":"HIGHPOINT SPORTING GOODS LLC","b":"","a":"44 CLOVE ROAD","c":"WANTAGE","s":"NJ","z":"07461","p":"9738755791","t":"01","lat":41.2292,"lng":-74.5992},{"n":"LETTING THE LEAD FLY LLC","b":"","a":"72 SHERMAN RIDGE RD","c":"WANTAGE","s":"NJ","z":"07461","p":"8623549034","t":"07","lat":41.2292,"lng":-74.5992},{"n":"ALPHA FIREARMS LLC","b":"","a":"126 ROSE MORROW RD","c":"WANTAGE","s":"NJ","z":"07461","p":"8457299388","t":"07","lat":41.2292,"lng":-74.5992},{"n":"FIREARMS EXPRESS LLC","b":"","a":"6 EVERGREEN ROAD","c":"SUSSEX","s":"NJ","z":"07461","p":"2019535313","t":"07","lat":41.2292,"lng":-74.5992},{"n":"TRI STATE FIREARMS EXCHANGE LLC","b":"","a":"280 STATE RT 94 UNIT #1","c":"VERNON","s":"NJ","z":"07462","p":"9737374016","t":"01","lat":41.185,"lng":-74.5332},{"n":"DYNAMIC COMBAT SOLUTIONS, LLC","b":"","a":"19 ANDOVER DRIVE","c":"WAYNE","s":"NJ","z":"07470","p":"8622901105","t":"01","lat":40.9471,"lng":-74.2466},{"n":"ELITE ARMS CONSULTING LLC","b":"","a":"1480 ALPS ROAD","c":"WAYNE","s":"NJ","z":"07470","p":"9739977117","t":"01","lat":40.9471,"lng":-74.2466},{"n":"DEVILS ARMORY LLC","b":"","a":"46 HIGH ST","c":"WAYNE","s":"NJ","z":"07470","p":"2012184505","t":"01","lat":40.9471,"lng":-74.2466},{"n":"BOLT CARRIER GUN EXCHANGE LLC","b":"","a":"1341 HAMBURG TURNPIKE L-6","c":"WAYNE","s":"NJ","z":"07470","p":"9737065288","t":"07","lat":40.9471,"lng":-74.2466},{"n":"RELOADERZNJ LLC","b":"","a":"1813 ROUTE 23 SOUTH","c":"WAYNE","s":"NJ","z":"07470","p":"9736943432","t":"07","lat":40.9471,"lng":-74.2466},{"n":"PEW PEW R US LLC","b":"","a":"809 VALLEY RD","c":"WAYNE","s":"NJ","z":"07470","p":"6093695325","t":"07","lat":40.9471,"lng":-74.2466},{"n":"VIA ARMA LLC","b":"","a":"140 BIRCHWOOD TERRACE","c":"WAYNE","s":"NJ","z":"07470","p":"9087050499","t":"07","lat":40.9471,"lng":-74.2466},{"n":"HAWKEYE CONSULTING LLC","b":"","a":"65 MOUNTAINVIEW BLVD","c":"WAYNE","s":"NJ","z":"07470","p":"9734172026","t":"07","lat":40.9471,"lng":-74.2466},{"n":"VIA ARMA LLC","b":"","a":"140 BIRCHWOOD TERRACE","c":"WAYNE","s":"NJ","z":"07470","p":"9087050499","t":"08","lat":40.9471,"lng":-74.2466},{"n":"WRIGHT TO BEAR ARMS LLC","b":"","a":"31 JOHN STREET","c":"WEST MILFORD","s":"NJ","z":"07480","p":"9736176048","t":"01","lat":41.0915,"lng":-74.375},{"n":"SCIUTO, STEVEN","b":"SCIUTO ARMS","a":"16 MILFORD LN","c":"WEST MILFORD","s":"NJ","z":"07480","p":"9737664532","t":"01","lat":41.0915,"lng":-74.375},{"n":"POLICE PRODUCTS CORPORATION","b":"","a":"540 RAVINE CT","c":"WYCKOFF","s":"NJ","z":"07481","p":"2014472900","t":"01","lat":40.9978,"lng":-74.166},{"n":"G \u0026 S HUNTERS LLC","b":"","a":"438 MAIN ST","c":"PATERSON","s":"NJ","z":"07501","p":"9733454100","t":"01","lat":40.9143,"lng":-74.1671},{"n":"G\u0026S HUNTERS LLC","b":"","a":"438 MAIN STREET","c":"PATERSON","s":"NJ","z":"07501","p":"9733454100","t":"07","lat":40.9143,"lng":-74.1671},{"n":"G \u0026 S HUNTERS LLC","b":"","a":"438 MAIN STREET","c":"PATERSON","s":"NJ","z":"07501","p":"9733454100","t":"08","lat":40.9143,"lng":-74.1671},{"n":"RIGHT GUN BENT FIREARMS CLEANING \u0026 MAINTENANCE LLC","b":"","a":"118 LEE AVE","c":"HAWTHORNE","s":"NJ","z":"07506","p":"6314959182","t":"01","lat":40.9564,"lng":-74.1569},{"n":"STASHERS FIREARMS LLC","b":"","a":"345 CENTRAL AVE","c":"HAWTHORNE","s":"NJ","z":"07506","p":"5514820016","t":"01","lat":40.9564,"lng":-74.1569},{"n":"PASSAIC COUNTY TARGET SPORTS LLC","b":"","a":"350 W CLINTON ST","c":"HALEDON","s":"NJ","z":"07508","p":"9737254491","t":"01","lat":40.9457,"lng":-74.1826},{"n":"SOME\u0027S WORLDWIDE UNIFORMS INC","b":"","a":"314 MAIN STREET","c":"HACKENSACK","s":"NJ","z":"07601","p":"2018431199","t":"01","lat":40.8882,"lng":-74.050299999999993},{"n":"CARRY ON ENTERPRISES LLC","b":"","a":"25 PALISADE AVE","c":"EMERSON","s":"NJ","z":"07630","p":"2012475357","t":"01","lat":40.9755,"lng":-74.0285},{"n":"GARDEN STATE GUNS LLC","b":"","a":"28 ELM STREET","c":"HARRINGTON PARK","s":"NJ","z":"07640","p":"2018033501","t":"01","lat":40.9918,"lng":-73.98},{"n":"BLACKWOOD CLUB NORTHVALE LLC","b":"","a":"266 UNION STREET","c":"NORTHVALE","s":"NJ","z":"07647","p":"2013136964","t":"07","lat":41.0086,"lng":-73.9389},{"n":"OTTOMANELLI\u0027S SPORTING ARMS, LLC","b":"OTTOMANELLI\u0027S SPORTING ARMS II","a":"143 RT 4","c":"PARAMUS","s":"NJ","z":"07652","p":"9732563070","t":"07","lat":40.9477,"lng":-74.0672},{"n":"PATRIOT ARMS LLC","b":"","a":"16 W PINE DR","c":"PARK RIDGE","s":"NJ","z":"07656","p":"2014974056","t":"01","lat":41.0343,"lng":-74.0396},{"n":"GRANITO GREENHOUSES INC","b":"BERGEN SPORTING GOODS","a":"649 BERGEN BLVD","c":"RIDGEFIELD","s":"NJ","z":"07657","p":"2019412666","t":"01","lat":40.8326,"lng":-74.0015},{"n":"TWIN ARMORY LLC","b":"","a":"505 SADDLE RIVER ROAD SECOND FLOOR UNIT H","c":"SADDLE BROOK","s":"NJ","z":"07663","p":"2015468001","t":"07","lat":40.9031,"lng":-74.0955},{"n":"ICONIC ARMS NEW JERSEY, LLC","b":"CONTINENTAL MUNITIONS","a":"191 COUNTY RD UNIT 1S","c":"TENAFLY","s":"NJ","z":"07670","p":"8774951911","t":"01","lat":40.9216,"lng":-73.9659},{"n":"ICONIC ARMS NEW JERSEY, LLC","b":"CONTINENTAL MUNITIONS","a":"191 COUNTY RD UNIT 1S","c":"TENAFLY","s":"NJ","z":"07670","p":"8774951911","t":"08","lat":40.9216,"lng":-73.9659},{"n":"SCULL, ARTURO","b":"NAVESINK GUNS","a":"16 RIDGEVIEW AVE","c":"ATLANTIC HIGHLANDS","s":"NJ","z":"07716","p":"7322917964","t":"01","lat":40.4015,"lng":-74.0309},{"n":"STR4PT GAMING LLC","b":"","a":"215 E END AVE","c":"BELFORD","s":"NJ","z":"07718","p":"9734456494","t":"01","lat":40.4173,"lng":-74.0889},{"n":"COMAN, ROBERT STEVENS","b":"COMAN FIREARMS","a":"3100 18TH AVE","c":"WALL","s":"NJ","z":"07719","p":"7324965243","t":"01","lat":40.1688,"lng":-74.072},{"n":"GRIGOLETTO, RONALD MARCO","b":"LEGACY FIREARMS","a":"3004 CLAYTON DR","c":"WALL","s":"NJ","z":"07719","p":"7322808750","t":"07","lat":40.1688,"lng":-74.072},{"n":"CHARLIE\u0027S SPORTING GOODS LLC","b":"","a":"57 JEROME AVE","c":"DEAL","s":"NJ","z":"07723","p":"9178865812","t":"01","lat":40.2506,"lng":-74.002},{"n":"CHARLIE\u0027S SPORTING GOODS, LLC","b":"","a":"57 JEROME AVE","c":"DEAL","s":"NJ","z":"07723","p":"9178865812","t":"08","lat":40.2506,"lng":-74.002},{"n":"HOGAN, RICHARD WILLIAM","b":"CABIN FIREARMS","a":"188 OAKLANDMILLS RD","c":"MANALAPAN","s":"NJ","z":"07726","p":"7325778986","t":"01","lat":40.2825,"lng":-74.3424},{"n":"FIREARMS FUNHOUSE GUNS \u0026 AMMO LLC","b":"","a":"2 SILVERLEAF WAY","c":"MANALAPAN","s":"NJ","z":"07726","p":"7328084867","t":"01","lat":40.2825,"lng":-74.3424},{"n":"PETRAZZOLO, DANIEL CHARLES","b":"DAN\u0027S GUN SHOP","a":"1 KEATS CT","c":"MANALAPAN","s":"NJ","z":"07726","p":"7328515790","t":"01","lat":40.2825,"lng":-74.3424},{"n":"SECURE FIREARMS LLC","b":"","a":"1 TORONTO WOODS RD","c":"MANALAPAN","s":"NJ","z":"07726","p":"9175678215","t":"01","lat":40.2825,"lng":-74.3424},{"n":"MONMOUTH ARMS LLC","b":"","a":"172 RT 9 N","c":"ENGLISHTOWN","s":"NJ","z":"07726","p":"7325471243","t":"01","lat":40.2825,"lng":-74.3424},{"n":"M \u0026 E FIREARMS LLC","b":"","a":"4 CONMACK LANE","c":"MANALAPAN","s":"NJ","z":"07726","p":"3472348204","t":"01","lat":40.2825,"lng":-74.3424},{"n":"ENGLISTOWN ARMORY LLC","b":"ENGLISHTOWN ARMORY \u0026 TOYS","a":"40 MAIN STREET SUITE 202","c":"ENGLISHTOWN","s":"NJ","z":"07726","p":"7325679941","t":"07","lat":40.2825,"lng":-74.3424},{"n":"MARTINO, ANTHONY JOSEPH","b":"FIREARMS FUNHOUSE GUNS \u0026 AMMO","a":"38 MAIN STREET","c":"ENGLISHTOWN","s":"NJ","z":"07726","p":"7328084867","t":"07","lat":40.2825,"lng":-74.3424},{"n":"MONMOUTH ARMS LLC","b":"","a":"172 US 9N SUITE F","c":"ENGLISHTOWN","s":"NJ","z":"07726","p":"7325471243","t":"07","lat":40.2825,"lng":-74.3424},{"n":"SALOMON, H EUGENE JR","b":"EH SALOMON SHOOTER\u0027S SUPPLIES","a":"142 YELLOW BROOK RD","c":"FARMINGDALE","s":"NJ","z":"07727","p":"9086750551","t":"01","lat":40.2043,"lng":-74.1779},{"n":"WONSALA, STANLEY W; RICHARD S; MICHAEL J","b":"SHOREGUNS","a":"1618 WYCKOFF RD","c":"FARMINGDALE","s":"NJ","z":"07727","p":"7328201515","t":"07","lat":40.2043,"lng":-74.1779},{"n":"SECOND SHOT TRADING LLC","b":"SECOND SHOT TRADING","a":"381 PLYMOUTH DRIVE","c":"FREEHOLD","s":"NJ","z":"07728","p":"7325807731","t":"01","lat":40.2458,"lng":-74.2768},{"n":"CASTRONOVA, DOMINIC A","b":"CASTRONOVAS GUN GARAGE","a":"113 SILOAM RD","c":"FREEHOLD","s":"NJ","z":"07728","p":"7324621996","t":"01","lat":40.2458,"lng":-74.2768},{"n":"FIREARM AND BALLISTICS ENGINEERING LLC","b":"","a":"150 BRITTANY DRIVE","c":"FREEHOLD","s":"NJ","z":"07728","p":"7325801736","t":"01","lat":40.2458,"lng":-74.2768},{"n":"DUNCAN DEFENSE CONSULTANTS LLC","b":"","a":"1332 STATE HIGHWAY 36","c":"HAZLET","s":"NJ","z":"07730","p":"7328986103","t":"07","lat":40.4226,"lng":-74.1799},{"n":"HOWELL GUN WORKS LLC","b":"","a":"2446 RT 9 S","c":"HOWELL","s":"NJ","z":"07731","p":"8484449400","t":"01","lat":40.1481,"lng":-74.2137},{"n":"ARESS, INC","b":"AMERICAN ARMORY","a":"6831 US 9","c":"HOWELL","s":"NJ","z":"07731","p":"7328862010","t":"07","lat":40.1481,"lng":-74.2137},{"n":"PRESTIGE LASER ENGRAVING LLC","b":"","a":"4 HAWK CT","c":"HOWELL","s":"NJ","z":"07731","p":"9083807978","t":"07","lat":40.1481,"lng":-74.2137},{"n":"FREEDOM USA AMMO LLC","b":"","a":"798 US-9","c":"HOWELL","s":"NJ","z":"07731","p":"7325750847","t":"07","lat":40.1481,"lng":-74.2137},{"n":"HOWELL GUN WORKS LLC","b":"","a":"2446 RT 9 S","c":"HOWELL","s":"NJ","z":"07731","p":"8484449400","t":"07","lat":40.1481,"lng":-74.2137},{"n":"GSD COATINGS LLC","b":"MODERN MATERIEL","a":"2 INDUSTRIAL DR STE G","c":"KEYPORT","s":"NJ","z":"07735","p":"7324566665","t":"07","lat":40.4332,"lng":-74.1996},{"n":"KEYPORT GUNS AND SPORTING GOODS, LLC","b":"KEYPORT GUNS AND SPORTING GOODS","a":"58 WEST FRONT STREET","c":"KEYPORT","s":"NJ","z":"07735","p":"7322171494","t":"01","lat":40.4332,"lng":-74.1996},{"n":"KEYPORT GUNS AND SPORTING GOODS, LLC","b":"KEYPORT GUNS AND SPORTING GOODS","a":"58 WEST FRONT STREET","c":"KEYPORT","s":"NJ","z":"07735","p":"7322171494","t":"07","lat":40.4332,"lng":-74.1996},{"n":"ABERDEEN GUNS AND AMMO CORP","b":"","a":"1208 ROUTE 34 SUITE 13","c":"ABERDEEN","s":"NJ","z":"07747","p":"7327780783","t":"01","lat":40.4109,"lng":-74.238},{"n":"ABERDEEN GUNS AND AMMO CORP","b":"","a":"1208 ROUTE 34 SUITE 13","c":"ABERDEEN","s":"NJ","z":"07747","p":"7327780783","t":"07","lat":40.4109,"lng":-74.238},{"n":"LEGEND FIREARMS LLC","b":"","a":"389 ROUTE 79 BUILDING 1","c":"MORGANVILLE","s":"NJ","z":"07751","p":"9082162915","t":"01","lat":40.3529,"lng":-74.2779},{"n":"SCHNEIDER MACHINE CO LLC","b":"SMC GUNSMITH LLC","a":"199 MAPLE AVE","c":"NEPTUNE","s":"NJ","z":"07753","p":"7326427263","t":"01","lat":40.2096,"lng":-74.0714},{"n":"T \u0026 R TACTICAL, WEAPONS AND CONSULTING LLC","b":"","a":"635 SOUTH RIVERSIDE DRIVE","c":"NEPTUNE","s":"NJ","z":"07753","p":"7327965356","t":"01","lat":40.2096,"lng":-74.0714},{"n":"MIDDLETOWN ARMS COMPANY \u0026 SPORTING GOODS LLC","b":"MIDDLETOWN ARMS CO \u0026 SPORTING GOODS","a":"429 NJ -36 N UNIT 4","c":"PORT MONMOUTH","s":"NJ","z":"07758","p":"7187153652","t":"07","lat":40.4289,"lng":-74.1083},{"n":"JFA ARMS \u0026 SPORTING SUPPLIES LLC","b":"","a":"48 FIRST STREET","c":"RUMSON","s":"NJ","z":"07760","p":"9734521071","t":"01","lat":40.3707,"lng":-74.0084},{"n":"OUTDOORS CAPITAL ADVENTURES INC","b":"ANDOVER HUNT AND FISH","a":"196 MAIN ST US HIGHWAY 206","c":"ANDOVER","s":"NJ","z":"07821","p":"9737867382","t":"01","lat":40.9614,"lng":-74.7524},{"n":"GRIFFIN \u0026 HOWE INC","b":"GRIFFIN \u0026 HOWE","a":"270 STANHOPE SPARTA RD","c":"ANDOVER","s":"NJ","z":"07821","p":"9733982670","t":"01","lat":40.9614,"lng":-74.7524},{"n":"GRIFFIN \u0026 HOWE INC","b":"GRIFFIN \u0026 HOWE","a":"270 STANHOPE SPARTA RD","c":"ANDOVER","s":"NJ","z":"07821","p":"9733982670","t":"07","lat":40.9614,"lng":-74.7524},{"n":"GRIFFIN \u0026 HOWE INC","b":"GRIFFIN \u0026 HOWE","a":"270 STANHOPE SPARTA ROAD","c":"ANDOVER","s":"NJ","z":"07821","p":"9733982670","t":"08","lat":40.9614,"lng":-74.7524},{"n":"WACKER\u0027S GREAT OUTDOORS LLC","b":"","a":"1 DICKERSON RD","c":"AUGUSTA","s":"NJ","z":"07822","p":"9739193397","t":"01","lat":41.1451,"lng":-74.6848},{"n":"SKYLANDS SPORT, INC","b":"SKYLANDS SPORT SHOP","a":"33 US HIGHWAY 206, SUITE 104","c":"AUGUSTA","s":"NJ","z":"07822","p":"9733005883","t":"01","lat":41.1451,"lng":-74.6848},{"n":"B AND H OUTDOOR SPORTING SUPPLIES LLC","b":"STOKES FOREST SPORT SHOP","a":"29 ROUTE 206 SOUTH","c":"SANDYSTON","s":"NJ","z":"07826","p":"9739485448","t":"01","lat":41.1705,"lng":-74.75},{"n":"JOCKEY HOLLOW SPORTING LLC","b":"","a":"2 FOX RUN RD","c":"CALIFON","s":"NJ","z":"07830","p":"9085078300","t":"01","lat":40.7162,"lng":-74.8152},{"n":"SIDE BY SIDE FIREARMS INC","b":"","a":"18 E MAIN ST","c":"DENVILLE","s":"NJ","z":"07834","p":"9736272848","t":"01","lat":40.8897,"lng":-74.4844},{"n":"PEQUEST SPORTING GOODS LLC","b":"","a":"290 RT 46","c":"GREAT MEADOWS","s":"NJ","z":"07838","p":"9087993530","t":"01","lat":40.852,"lng":-74.9418},{"n":"COBRA ONE TACTICAL, LLC","b":"","a":"330A RT 46","c":"GREAT MEADOWS","s":"NJ","z":"07838","p":"9082962474","t":"07","lat":40.852,"lng":-74.9418},{"n":"HACKETTSTOWN FIREARM STORAGE LLC","b":"","a":"134 MAIN ST","c":"HACKETTSTOWN","s":"NJ","z":"07840","p":"9088525260","t":"01","lat":40.8529,"lng":-74.8343},{"n":"SUSSEX GUN WORKS LLC","b":"GOOD GUYS GUNS NJ","a":"762 ROUTE 15 - UNIT 1D","c":"LAKE HOPATCONG","s":"NJ","z":"07849","p":"9739704848","t":"07","lat":40.9506,"lng":-74.6129},{"n":"THE SHOOTERS CORNER INC","b":"","a":"8 NEW JERSEY AVE","c":"LAKE HOPATCONG","s":"NJ","z":"07849","p":"9736635159","t":"01","lat":40.9506,"lng":-74.6129},{"n":"SUZANSKY, JAMES W","b":"LONG VALLEY WATNOTS \u0026 GOWITS CO","a":"65 W VALLEY BROOK RD","c":"LONG VALLEY","s":"NJ","z":"07853","p":"9088764834","t":"01","lat":40.7878,"lng":-74.787},{"n":"ULLMANN, KURT CHARLES","b":"ARTISAN GUN WORKS","a":"139 GREENDELL ROAD","c":"NEWTON","s":"NJ","z":"07860","p":"9738626092","t":"01","lat":41.0695,"lng":-74.8069},{"n":"SEAGER, EDWARD WALTHER","b":"","a":"10 WALNUT TRAIL","c":"NEWTON","s":"NJ","z":"07860","p":"2013234871","t":"01","lat":41.0695,"lng":-74.8069},{"n":"WACKER\u0027S GREAT OUTDOORS LLC","b":"WACKER\u0027S SPORT SHOP SUSSEX ARMS","a":"89 HAMPTON HOUSE RD","c":"NEWTON","s":"NJ","z":"07860","p":"9739193397","t":"07","lat":41.0695,"lng":-74.8069},{"n":"SIMON PETER FISHING TACKLE \u0026 SPORT CO INC","b":"","a":"660 ROUTE 206 SOUTH","c":"NEWTON","s":"NJ","z":"07860","p":"9737865313","t":"07","lat":41.0695,"lng":-74.8069},{"n":"THE ANDOVER ARMS GUNSMITH LLC","b":"","a":"98A ANDOVER SPARTA RD","c":"NEWTON","s":"NJ","z":"07860","p":"8624537202","t":"07","lat":41.0695,"lng":-74.8069},{"n":"JONES, BRUCE R","b":"BRUCE R JONES GUNSMITHING","a":"4 RAVINE DR ANDOVER TWSP","c":"NEWTON","s":"NJ","z":"07860","p":"2013174971","t":"01","lat":41.0695,"lng":-74.8069},{"n":"SPECIALTY AMERICAN WEAPONS LLC","b":"SAW","a":"229 BUCKLEY AVE","c":"OXFORD","s":"NJ","z":"07863","p":"9084533938","t":"08","lat":40.8105,"lng":-75.0019},{"n":"SILVER BULLET SUPPLY LLC","b":"","a":"20 WALL ST","c":"ROCKAWAY","s":"NJ","z":"07866","p":"9736649661","t":"01","lat":40.9229,"lng":-74.5094},{"n":"SILVER BULLET SUPPLY LLC","b":"","a":"20 WALL ST","c":"ROCKAWAY","s":"NJ","z":"07866","p":"9736649661","t":"07","lat":40.9229,"lng":-74.5094},{"n":"GUNSHUB COM LLC","b":"","a":"961 ROUTE 10 E UNIT 2F","c":"RANDOLPH","s":"NJ","z":"07869","p":"8446583729","t":"01","lat":40.8456,"lng":-74.5725},{"n":"IC INDUSTRIES, LLC","b":"BUDDY ARMS","a":"48 SANFORD DRIVE","c":"RANDOLPH","s":"NJ","z":"07869","p":"9737696281","t":"01","lat":40.8456,"lng":-74.5725},{"n":"RTSP LLC","b":"","a":"961 STATE RT 10 E UNIT 2F","c":"RANDOLPH","s":"NJ","z":"07869","p":"9734347600","t":"07","lat":40.8456,"lng":-74.5725},{"n":"PRZYBYSZEWSKI, LEON JR \u0026 LEON III","b":"LEE \u0026 SONS SPORT SHOPPE","a":"116 RT 206","c":"STANHOPE","s":"NJ","z":"07874","p":"8622999177","t":"01","lat":40.9217,"lng":-74.7004},{"n":"PATRIOTS\u0027 PATH COUNCIL, INC BOY SCOUTS OF AMERICA","b":"","a":"750 WATERLOO ROAD","c":"STANHOPE","s":"NJ","z":"07874","p":"9737659322","t":"01","lat":40.9217,"lng":-74.7004},{"n":"RAMSEY OUTDOOR STORE INC","b":"","a":"281 ROUTE 10 EAST  #16","c":"SUCCASUNNA","s":"NJ","z":"07876","p":"9735847799","t":"01","lat":40.8539,"lng":-74.6536},{"n":"GUN TOWN USA LLC","b":"","a":"1056 HARMONY BRASS CASTLE RD","c":"WASHINGTON","s":"NJ","z":"07882","p":"9082469643","t":"01","lat":40.7582,"lng":-74.9914},{"n":"GUN TOWN USA LLC","b":"","a":"1056 HARMONY BRASS CASTLE RD","c":"WASHINGTON","s":"NJ","z":"07882","p":"9082469643","t":"07","lat":40.7582,"lng":-74.9914},{"n":"ARMORYIQ LLC","b":"","a":"46 KAREN WAY","c":"SUMMIT","s":"NJ","z":"07901","p":"7172656662","t":"07","lat":40.7149,"lng":-74.3642},{"n":"COBB, IRA STEPHEN","b":"","a":"1115 RT 202 \u0026 206","c":"BEDMINSTER","s":"NJ","z":"07921","p":"9084329813","t":"01","lat":40.6571,"lng":-74.6432},{"n":"BEAR FIREARMS INC","b":"","a":"7 LARISON ROAD","c":"CHESTER","s":"NJ","z":"07930","p":"9733322526","t":"01","lat":40.7892,"lng":-74.6776},{"n":"YYDS ARMORY LLC","b":"","a":"39 E FOX CHASE RD","c":"CHESTER","s":"NJ","z":"07930","p":"9088872727","t":"07","lat":40.7892,"lng":-74.6776},{"n":"INTERNATIONAL MILITARY ANTIQUES INC","b":"IMA","a":"1000 VALLEY RD","c":"GILLETTE","s":"NJ","z":"07933","p":"9089031200","t":"08","lat":40.6877,"lng":-74.4681},{"n":"AMERICAN FIREARMS LLC","b":"","a":"11 KENNEDY TERRACE","c":"EAST HANOVER","s":"NJ","z":"07936","p":"9734288778","t":"01","lat":40.8192,"lng":-74.3636},{"n":"COUNTY LINE FIREARMS LLC","b":"","a":"393 RT 10 E","c":"EAST HANOVER","s":"NJ","z":"07936","p":"9739851906","t":"01","lat":40.8192,"lng":-74.3636},{"n":"POINT BLANK GUNS AND AMMO LLC","b":"","a":"393 RT 10 EAST SUITE B","c":"EAST HANOVER","s":"NJ","z":"07936","p":"9737537733","t":"07","lat":40.8192,"lng":-74.3636},{"n":"JETAGENT, LLC","b":"","a":"4 VALLEY VIEW DR","c":"MENDHAM","s":"NJ","z":"07945","p":"9089386510","t":"01","lat":40.7789,"lng":-74.6},{"n":"INTERTEK LABORATORIES INC","b":"","a":"340 UNION ST","c":"STIRLING","s":"NJ","z":"07980","p":"9089031800","t":"01","lat":40.6774,"lng":-74.4968},{"n":"INTERTEK LABORATORIES INC","b":"","a":"340 UNION ST","c":"STIRLING","s":"NJ","z":"07980","p":"9089031800","t":"07","lat":40.6774,"lng":-74.4968},{"n":"IRON FIST DEFENSE GROUP LLC","b":"","a":"1810 FIRESIDE LN","c":"CHERRY HILL","s":"NJ","z":"08003","p":"2152063000","t":"07","lat":39.8805,"lng":-74.9706},{"n":"TJS BLUING \u0026 SMITHING, LLC","b":"","a":"9 CHERYL ANN CT","c":"BERLIN","s":"NJ","z":"08009","p":"6098200837","t":"01","lat":39.7788,"lng":-74.9308},{"n":"WINTERS, JOSEPH B \u0026 JORDAN, KATHLEEN L","b":"WINTERS SPECIALITIES","a":"15 SOUTH ATLANTIC AVE","c":"BERLIN","s":"NJ","z":"08009","p":"8567670349","t":"01","lat":39.7788,"lng":-74.9308},{"n":"A J FIREARMS TACTICAL AND TRAINING LLC","b":"","a":"339 NRT 73 SUITE 7","c":"BERLIN","s":"NJ","z":"08009","p":"6092344619","t":"07","lat":39.7788,"lng":-74.9308},{"n":"SCHIAVO OUTDOORS LLC","b":"KNM ARCHERY","a":"333 BARBARA DRIVE","c":"CLARKSBORO","s":"NJ","z":"08020","p":"8562925424","t":"01","lat":39.7992,"lng":-75.2237},{"n":"ABIUSO, JOSEPH","b":"J\u0026J GUNWORKS","a":"310 WHITE HORSE PIKE","c":"CLEMENTON","s":"NJ","z":"08021","p":"8567841910","t":"01","lat":39.8036,"lng":-75.0058},{"n":"ALDARAD ARMS, LLC","b":"","a":"650 CHESTNUT AVENUE","c":"LAUREL SPRINGS","s":"NJ","z":"08021","p":"8564667849","t":"07","lat":39.8036,"lng":-75.0058},{"n":"MUNYAN, RONALD A","b":"IKES GUN SHOP","a":"216 CRESCENT AVE","c":"GIBBSTOWN","s":"NJ","z":"08027","p":"8564232262","t":"01","lat":39.8231,"lng":-75.2751},{"n":"BOB\u0027S LITTLE SPORT SHOP INC","b":"BLSS","a":"316 DELSEA DR N","c":"GLASSBORO","s":"NJ","z":"08028","p":"8568817575","t":"07","lat":39.7068,"lng":-75.1172},{"n":"GARDEN STATE ADMINISTRATIVE SOLUTIONS INC","b":"","a":"856 SOUTH WHITE HORSE PIKE SUITE 1","c":"HAMMONTON","s":"NJ","z":"08037","p":"6098783516","t":"01","lat":39.638,"lng":-74.7728},{"n":"JJ FIREARMS LLC","b":"","a":"792 ELEVENTH ST","c":"HAMMONTON","s":"NJ","z":"08037","p":"6095619455","t":"01","lat":39.638,"lng":-74.7728},{"n":"SWEETWATER CUSTOM COATINGS, LLC","b":"","a":"4501 PLEASANT MILLS RD","c":"HAMMONTON","s":"NJ","z":"08037","p":"6098393455","t":"01","lat":39.638,"lng":-74.7728},{"n":"WHITTAKER, JAMES C JR","b":"WHITTAKER ARMS","a":"1456 BACKLINE RD","c":"FOLSOM","s":"NJ","z":"08037","p":"6094322367","t":"07","lat":39.638,"lng":-74.7728},{"n":"RIVERA, SCOTT","b":"SWAT FIREARMS","a":"339 NORTH CHEW ROAD","c":"HAMMONTON","s":"NJ","z":"08037","p":"6092263172","t":"07","lat":39.638,"lng":-74.7728},{"n":"FLYER 30 ENTERPRISES LLC","b":"GARDEN STATE FIREARMS","a":"42 FOLWELL STATION RD","c":"JOBSTOWN","s":"NJ","z":"08041","p":"6094170255","t":"01","lat":40.0387,"lng":-74.6873},{"n":"TROUT\u0027S GUNSHOP LLC","b":"","a":"452 JULIUSTOWN GEORGETOWN RD  PO BOX 35","c":"JULIUSTOWN","s":"NJ","z":"08042","p":"6098942727","t":"01","lat":40.0123,"lng":-74.6646},{"n":"GARDEN STATE SPORTS CENTER LLC","b":"","a":"1226 HADDONFIELD BERLIN ROAD","c":"VOORHEES","s":"NJ","z":"08043","p":"8567670700","t":"01","lat":39.8504,"lng":-74.9646},{"n":"J\u0026E GUNWORKS LLC","b":"","a":"1603 RT 38 UNIT 4","c":"LUMBERTON","s":"NJ","z":"08048","p":"6092612003","t":"07","lat":39.9651,"lng":-74.8067},{"n":"P \u0026 K FIREARMS \u0026 AMMO INC","b":"","a":"63 EAST BAY AVE","c":"MANAHAWKIN","s":"NJ","z":"08050","p":"6095974646","t":"01","lat":39.705,"lng":-74.2604},{"n":"TITAN FIREARMS AND COLLECTABLES LLC","b":"","a":"299 MORRIS BLVD","c":"MANAHAWKIN","s":"NJ","z":"08050","p":"2012304344","t":"01","lat":39.705,"lng":-74.2604},{"n":"STAFFORD FIREARMS SAFETY TRAINING LLC","b":"","a":"289 BULKHEAD AVENUE","c":"MANAHAWKIN","s":"NJ","z":"08050","p":"6099780388","t":"01","lat":39.705,"lng":-74.2604},{"n":"PARABELLUM INDUSTRIES UNLIMITED LLC","b":"PARABELLUM ARMORY","a":"472 OUTRIGGER LANE","c":"MANAHAWKIN","s":"NJ","z":"08050","p":"6093849414","t":"07","lat":39.705,"lng":-74.2604},{"n":"LEGACY INDOOR RANGE AND ARMORY LLC","b":"","a":"2864 ROUTE 73 NORTH","c":"MAPLE SHADE","s":"NJ","z":"08052","p":"8564992917","t":"07","lat":39.9511,"lng":-74.9946},{"n":"URBAN TACTICAL OF SOUTH JERSEY LLC","b":"","a":"65 E RTE 70, UNIT 9A","c":"MARLTON","s":"NJ","z":"08053","p":"8567804447","t":"07","lat":39.8845,"lng":-74.9067},{"n":"ACTIVE RESPONSE, LLC","b":"","a":"60 SOUTH MAIN STREET UNIT B","c":"MEDFORD","s":"NJ","z":"08055","p":"6096781055","t":"01","lat":39.8637,"lng":-74.8223},{"n":"THE WAY IT WAS SPORTING SERVICES INC","b":"","a":"620 CHESTNUT ST","c":"MOORESTOWN","s":"NJ","z":"08057","p":"8562310111","t":"01","lat":39.9683,"lng":-74.9533},{"n":"SUSINSKI, MICHAEL JOESPH","b":"STURMGEWEHR ORDNANCE","a":"155 SHARPLESS BLVD","c":"WESTAMPTON","s":"NJ","z":"08060","p":"7327792644","t":"01","lat":40.0086,"lng":-74.7896},{"n":"GRACE, JAMES KYLE","b":"","a":"214 IRICK ROAD","c":"WESTAMPTON","s":"NJ","z":"08060","p":"6092886895","t":"01","lat":40.0086,"lng":-74.7896},{"n":"CONCEALED CARRY ACADEMY LLC","b":"","a":"521 HOMESTEAD AVE","c":"MOUNT HOLLY","s":"NJ","z":"08060","p":"6092766373","t":"07","lat":40.0086,"lng":-74.7896},{"n":"CARLIN, CHARLES F III","b":"SOUTH JERSEY FIREARMS","a":"5 HIGH MEADOWS DR","c":"MULLICA HILL","s":"NJ","z":"08062","p":"8569522189","t":"01","lat":39.7252,"lng":-75.2065},{"n":"HOAGLAND, RICHARD S","b":"HOAGLAND FIREARMS","a":"222 WILLIAMSON LN","c":"MULLICA HILL","s":"NJ","z":"08062","p":"8565892288","t":"01","lat":39.7252,"lng":-75.2065},{"n":"BIG IGLOO ARMORY LLC","b":"","a":"72 HANOVER STREET","c":"PEMBERTON","s":"NJ","z":"08068","p":"6092830039","t":"07","lat":39.9712,"lng":-74.6676},{"n":"COUNTY SPORTS LLC","b":"","a":"622 CEDAR CREST DR","c":"CARNEYS POINT","s":"NJ","z":"08069","p":"8562991982","t":"01","lat":39.6994,"lng":-75.4495},{"n":"THE BOAT EXCHANGE OF SALEM LLC","b":"SALEM BOAT EXCHANGE","a":"1163 S BROADWAY","c":"PENNSVILLE","s":"NJ","z":"08070","p":"8569352515","t":"01","lat":39.6491,"lng":-75.5155},{"n":"OBUCHOWSKI, JOHN GEORGE","b":"","a":"3116 CONCORD DR","c":"CINNAMINSON","s":"NJ","z":"08077","p":"8568299637","t":"01","lat":40.002,"lng":-74.9952},{"n":"H\u0026M TACTICAL SUPPLY LLC","b":"","a":"338 WALNUT STREET ROAD","c":"SALEM","s":"NJ","z":"08079","p":"6093641737","t":"01","lat":39.5591,"lng":-75.4521},{"n":"HILL, ANDREW","b":"HAWK CUSTOM","a":"849 HAWK BRIDGE RD","c":"SALEM","s":"NJ","z":"08079","p":"8562992800","t":"07","lat":39.5591,"lng":-75.4521},{"n":"FOGG, JAMES E","b":"JIM FOGG GUNSMITH","a":"419 POINTERS AUBURN RD","c":"SALEM","s":"NJ","z":"08079","p":"8567690892","t":"01","lat":39.5591,"lng":-75.4521},{"n":"BTL SUPPLY LLC","b":"","a":"739 MAIN STREET","c":"SEWELL","s":"NJ","z":"08080","p":"8564720446","t":"01","lat":39.7473,"lng":-75.0899},{"n":"BODNAR, ALBERT F JR","b":"WEAPONS AND ACCESSORIES","a":"14 ALBERTA COURT","c":"SEWELL","s":"NJ","z":"08080","p":"8565894403","t":"01","lat":39.7473,"lng":-75.0899},{"n":"ESQUIRE ESTATE FIREARMS \u0026 COLLECTIBLES LLC","b":"EEFC LLC ESQUIRE FIREARMS BREDA USA MAROCCHI USA","a":"975 BRIDGETON PIKE, SUITE A","c":"SEWELL","s":"NJ","z":"08080","p":"6092546480","t":"01","lat":39.7473,"lng":-75.0899},{"n":"ESQUIRE ESTATE FIREARMS \u0026 COLLECTIBLES LLC","b":"EEFC LLC ESQUIRE FIREARMS BREDA USA MAROCCHI USA","a":"975 BRIDGETON PIKE, SUITE A","c":"SEWELL","s":"NJ","z":"08080","p":"6092546480","t":"07","lat":39.7473,"lng":-75.0899},{"n":"MAD WOLF USA LLC","b":"","a":"623 E PRESTON AVE","c":"SOMERDALE","s":"NJ","z":"08083","p":"4847560559","t":"07","lat":39.84,"lng":-75.0309},{"n":"ON POINT SHOOTING LLC","b":"","a":"143 RULON ROAD UNIT 2","c":"WOOLWICH","s":"NJ","z":"08085","p":"8567160050","t":"07","lat":39.7529,"lng":-75.3362},{"n":"MORRIS, THOMAS JOSEPH III","b":"EAGLE POINT GUN / TJ MORRIS \u0026 SONS","a":"1707 THIRD STREET","c":"THOROFARE","s":"NJ","z":"08086","p":"8568486945","t":"07","lat":39.8457,"lng":-75.1943},{"n":"FREEDOM AMMO LLC","b":"","a":"700 CROWN POINT RD","c":"WEST DEPTFORD","s":"NJ","z":"08086","p":"8568482666","t":"07","lat":39.8457,"lng":-75.1943},{"n":"MORRIS, THOMAS J III","b":"EAGLE POINT GUN/ T J MORRIS \u0026 SONS","a":"1707 THIRD ST","c":"THOROFARE","s":"NJ","z":"08086","p":"8568486945","t":"01","lat":39.8457,"lng":-75.1943},{"n":"PAGE, JEFFREY CHARLES","b":"AJP WEAPONS F/X","a":"28 ST ANDREWS DR","c":"LITTLE EGG HARBOR","s":"NJ","z":"08087","p":"6094891333","t":"01","lat":39.5881,"lng":-74.3646},{"n":"GEORGE J PETRONIS ENTERPRISES INC","b":"THE GUN SHOP","a":"60 #D MAIN ST","c":"VINCENTOWN","s":"NJ","z":"08088","p":"6098591997","t":"01","lat":39.8604,"lng":-74.6693},{"n":"PISTOL PETE\u0027S GUN SHOP INC","b":"","a":"4 PARK DR","c":"SHAMONG","s":"NJ","z":"08088","p":"6093514877","t":"01","lat":39.8604,"lng":-74.6693},{"n":"TACTICAL PUBLIC SAFETY LLC","b":"","a":"1036 INDUSTRIAL DR","c":"WEST BERLIN","s":"NJ","z":"08091","p":"8567683336","t":"01","lat":39.8051,"lng":-74.9255},{"n":"SHOOTERS HARDWARE LLC","b":"SHOOTERS POINT 5","a":"218 MAIN STREET","c":"WEST CREEK","s":"NJ","z":"08092","p":"6092964080","t":"07","lat":39.6627,"lng":-74.2885},{"n":"VALENTINE FIREARMS TRAINING LLC","b":"","a":"300 THOMAS AVE BUILDING 401","c":"WILLIAMSTOWN","s":"NJ","z":"08094","p":"6093157538","t":"01","lat":39.665,"lng":-74.971},{"n":"HENJ ENTERPRISES LLC","b":"HIGH END ARMORY","a":"1982 N BLACKHORSE PIKE","c":"WILLIAMSTOWN","s":"NJ","z":"08094","p":"8563334867","t":"07","lat":39.665,"lng":-74.971},{"n":"AYRES, RONALD BRIAN","b":"RON\u0027S TRANSFER COMPANY","a":"734 AYRES AVE","c":"DEPTFORD","s":"NJ","z":"08096","p":"6095029760","t":"01","lat":39.7539,"lng":-74.996},{"n":"THE ARSENAL GUN SHOP LLC","b":"","a":"1924 COOPER STREET","c":"DEPTFORD","s":"NJ","z":"08096","p":"8562324867","t":"07","lat":39.7539,"lng":-74.996},{"n":"CATALANO, JOHN PATRICK","b":"","a":"80 BLACK RD","c":"WOODSTOWN","s":"NJ","z":"08098","p":"6097744001","t":"01","lat":39.6457,"lng":-75.3248},{"n":"BILL\u0027S TRANSFERS AND TRAINING LLC","b":"","a":"135 E CEDAR AVE","c":"HADDON TOWNSHIP","s":"NJ","z":"08107","p":"6097924838","t":"01","lat":39.908,"lng":-75.0849},{"n":"TACTICAL SHOOTING CONCEPT LLC","b":"","a":"506 WESTMONT AVE","c":"WESTMONT","s":"NJ","z":"08108","p":"6096850175","t":"01","lat":39.9157,"lng":-75.0634},{"n":"ANUBIS ARMS LLC","b":"TITAN GUN WORKS","a":"6650 BROWNING ROAD, UNIT M-14B","c":"PENNSAUKEN","s":"NJ","z":"08109","p":"8563304772","t":"01","lat":39.9519,"lng":-75.0482},{"n":"ANUBIS ARMS LLC","b":"","a":"6650 BROWNING RD UNIT M-14B","c":"PENNSAUKEN","s":"NJ","z":"08109","p":"8564038225","t":"07","lat":39.9519,"lng":-75.0482},{"n":"RANGE 129 LLC","b":"","a":"129 PLEASANT AVENUE","c":"ABSECON","s":"NJ","z":"08201","p":"6093802557","t":"07","lat":39.4218,"lng":-74.4949},{"n":"SEA GEAR INDUSTRIAL SUPPLY LLC","b":"SEA GEAR MARINE OUTFITTERS","a":"795 RT 109","c":"CAPE MAY","s":"NJ","z":"08204","p":"6098840330","t":"01","lat":38.9711,"lng":-74.9214},{"n":"1791 FIREARMS LLC","b":"","a":"513A S SEAVIEW AVE","c":"GALLOWAY","s":"NJ","z":"08205","p":"2013949704","t":"07","lat":39.4745,"lng":-74.4575},{"n":"LANDS N GROOVES LLC","b":"","a":"175 STAGECOACH ROAD","c":"CAPE MAY COURT HOUSE","s":"NJ","z":"08210","p":"6094630534","t":"01","lat":39.1378,"lng":-74.7806},{"n":"POOLERCO LLC","b":"FRONTLINE SPORTS","a":"8 ROSIES LANE","c":"CAPE MAY COURT HOUSE","s":"NJ","z":"08210","p":"6092245462","t":"01","lat":39.1378,"lng":-74.7806},{"n":"SHORE BRAKE FIREARMS LLC","b":"","a":"30 OYSTER ROAD","c":"CAPE MAY COURT HOUSE","s":"NJ","z":"08210","p":"6092249988","t":"07","lat":39.1378,"lng":-74.7806},{"n":"OUTPOST SUPPLY LLC","b":"","a":"128 SOUTH GENOA AVE","c":"EGG HARBOR CITY","s":"NJ","z":"08215","p":"6094455994","t":"01","lat":39.5331,"lng":-74.6177},{"n":"ROUND SIX GUNSMITHING LLC","b":"","a":"10 S PRAGUE AVE","c":"EGG HARBOR CITY","s":"NJ","z":"08215","p":"6094455207","t":"07","lat":39.5331,"lng":-74.6177},{"n":"GOVE, RONALD C","b":"","a":"1000 ARGO LN","c":"NORTHFIELD","s":"NJ","z":"08225","p":"6094429326","t":"01","lat":39.3703,"lng":-74.5552},{"n":"SEAVILLE FIREARMS LLC","b":"","a":"1828 ROUTE 9","c":"SEAVILLE","s":"NJ","z":"08230","p":"6097753475","t":"01","lat":39.2154,"lng":-74.7075},{"n":"FULL METAL JACKET GUN RANGE LLC","b":"","a":"3018-B ROUTE 9","c":"SEAVILLE","s":"NJ","z":"08230","p":"6094276774","t":"07","lat":39.2154,"lng":-74.7075},{"n":"YALE CARTRIDGE COMPANY, LLC","b":"","a":"108 BRIDLE PATH DRIVE","c":"EGG HARBOR TOWNSHIP","s":"NJ","z":"08234","p":"6099046464","t":"08","lat":39.3741,"lng":-74.6118},{"n":"BEACHCOMBER COINS INC","b":"BEACHCOMBER COLLECTIBLES","a":"6692 BLACK HORSE PIKE","c":"EGG HARBOR TOWNSHIP","s":"NJ","z":"08234","p":"6096451031","t":"01","lat":39.3741,"lng":-74.6118},{"n":"UNITED UNIFORMS LLC","b":"IGY6 / IGY6 TACTICAL","a":"1050 RTE 47","c":"RIO GRANDE","s":"NJ","z":"08242","p":"6098499347","t":"07","lat":39.0196,"lng":-74.8756},{"n":"DANIELS, DAVID WAYNE","b":"DANGER ARMS","a":"1083 DENNISVILLE-PETERSBURG RD","c":"PETERSBURG","s":"NJ","z":"08270","p":"6098613719","t":"01","lat":39.2716,"lng":-74.7968},{"n":"BELLEPLAIN SUPPLY CO INC","b":"","a":"346 HANDSMILL RD","c":"BELLEPLAIN","s":"NJ","z":"08270","p":"6098612345","t":"01","lat":39.2716,"lng":-74.7968},{"n":"HUNTER\u0027S ARCHERY SUPPLY, LLC","b":"","a":"233 COBBS MILL RD","c":"BRIDGETON","s":"NJ","z":"08302","p":"6093194899","t":"07","lat":39.3762,"lng":-75.1617},{"n":"DGGS HOLDINGS LLC","b":"REILLYS GUNS, AMMO \u0026 SPORTS","a":"345 MAIN ST","c":"CEDARVILLE","s":"NJ","z":"08311","p":"8564473030","t":"07","lat":39.337,"lng":-75.1994},{"n":"TWICE BORN PROPERTIES LLC","b":"BENNETT FIREARMS","a":"117 MADISON AVE","c":"CLAYTON","s":"NJ","z":"08312","p":"8565135330","t":"01","lat":39.659,"lng":-75.0942},{"n":"THE ELMER GUN COMPANY LLC","b":"","a":"104 HUSTED STATION ROAD","c":"ELMER","s":"NJ","z":"08318","p":"8563641031","t":"07","lat":39.5691,"lng":-75.163},{"n":"HAGUES LLC","b":"","a":"313 WILLOW GROVE ROAD SUITE 100","c":"PITTSGROVE","s":"NJ","z":"08318","p":"8567122193","t":"01","lat":39.5691,"lng":-75.163},{"n":"BILOTTA, ROBERT AMEDEO","b":"MONROE WAFFEN","a":"2188 STANTON AVE","c":"FRANKLINVILLE","s":"NJ","z":"08322","p":"8566295414","t":"01","lat":39.6156,"lng":-75.0409},{"n":"ADAMS, DOUGLAS E","b":"HIDDEN ACRES FIREARMS","a":"232 ABERDEEN AVE","c":"LANDISVILLE","s":"NJ","z":"08326","p":"8569822980","t":"01","lat":39.5239,"lng":-74.9377},{"n":"LOCK AND LOAD GUNS \u0026 AMMO LLC","b":"","a":"35 STATION ROAD","c":"LEESBURG","s":"NJ","z":"08327","p":"6095795941","t":"01","lat":39.2568,"lng":-74.9874},{"n":"WHEATON, FRANK H III","b":"WHEATON AUTOMATIC ARMS","a":"1236 FRONT ST","c":"MAURICETOWN","s":"NJ","z":"08329","p":"8567853121","t":"07","lat":39.2853,"lng":-74.9983},{"n":"SPANKY\u0027S FIREARMS LLC","b":"","a":"528 WILLOW OAK DRIVE","c":"MAYS LANDING","s":"NJ","z":"08330","p":"6095175319","t":"01","lat":39.432,"lng":-74.6962},{"n":"BUCK TAILS OUTFITTERS LLC","b":"","a":"6390 HARDING HIGHWAY","c":"MAYS LANDING","s":"NJ","z":"08330","p":"6098292229","t":"07","lat":39.432,"lng":-74.6962},{"n":"SOUTH JERSEY GUN WORKS LLC","b":"","a":"6101 ORANGE ST","c":"MAYS LANDING","s":"NJ","z":"08330","p":"6098399391","t":"07","lat":39.432,"lng":-74.6962},{"n":"SEAN HOOVER LLC","b":"HOMELAND ARMORY","a":"6385 PINE STREET","c":"MAYS LANDING","s":"NJ","z":"08330","p":"6099484867","t":"07","lat":39.432,"lng":-74.6962},{"n":"SMITH \u0026 JACKSON MILITARY ANTIQUES \u0026 FIREARMS LLC","b":"","a":"21 PETERSON ST","c":"MILLVILLE","s":"NJ","z":"08332","p":"8563005288","t":"01","lat":39.3673,"lng":-75.0293},{"n":"TORELLI, JOHN","b":"JERSEY SMALL ARMS GUNSMITHING","a":"501 IRELAND AVE","c":"MILLVILLE","s":"NJ","z":"08332","p":"8568255766","t":"07","lat":39.3673,"lng":-75.0293},{"n":"45 ARMS AND AMMO LLC","b":"","a":"5 RENA ST","c":"NEWFIELD","s":"NJ","z":"08344","p":"2157687593","t":"07","lat":39.5553,"lng":-75.0276},{"n":"CRESCI ARMS LLC","b":"","a":"4708 LANDIS AVE","c":"VINELAND","s":"NJ","z":"08360","p":"8564056825","t":"07","lat":39.4818,"lng":-75.0091},{"n":"CORSIGLIA, ANTHONY T","b":"THE GUN RACK","a":"1726 N WEST BLVD","c":"VINELAND","s":"NJ","z":"08360","p":"8566924773","t":"01","lat":39.4818,"lng":-75.0091},{"n":"RR OUTDOORS LLC","b":"BUTCH\u0027S GUN WORLD","a":"2057 W LANDIS AVE","c":"VINELAND","s":"NJ","z":"08360","p":"8566921010","t":"07","lat":39.4818,"lng":-75.0091},{"n":"KURT IVES PRECISION LLC","b":"","a":"3003 NORTH MILL RD BLDG 100","c":"VINELAND","s":"NJ","z":"08360","p":"6097061673","t":"07","lat":39.4818,"lng":-75.0091},{"n":"BASS PRO OUTDOOR WORLD, LLC","b":"BASS PRO SHOPS OUTDOOR WORLD 065","a":"30 N CHRISTOPHER COLUMBUS BLVD","c":"ATLANTIC CITY","s":"NJ","z":"08401","p":"6094494500","t":"01","lat":39.3664,"lng":-74.4317},{"n":"LADY LIBERTY GUNSMITHING LLC","b":"","a":"121 N LACLEDE PLACE","c":"ATLANTIC CITY","s":"NJ","z":"08401","p":"6093481900","t":"01","lat":39.3664,"lng":-74.4317},{"n":"CHEYENNE MOUNTAIN OUTFITTERS LLC","b":"","a":"244 ROUTE 130","c":"BORDENTOWN","s":"NJ","z":"08505","p":"6095708430","t":"07","lat":40.1431,"lng":-74.7032},{"n":"KAU, CHRISTOPHER G","b":"DISTINCTIVE ARMS","a":"8 QUAIL HILL RD","c":"CLARKSBURG","s":"NJ","z":"08510","p":"7322418968","t":"01","lat":40.147,"lng":-74.609},{"n":"JAKTOOL LLC","b":"JEVEK SOLUTIONS","a":"259 PROSPECT PLAINS ROAD BUILDING B","c":"CRANBURY","s":"NJ","z":"08512","p":"6096642451","t":"07","lat":40.3039,"lng":-74.5065},{"n":"ASCIONE, GEORGE","b":"D R A TECHNOLOGIES","a":"579 RT 539","c":"CREAM RIDGE","s":"NJ","z":"08514","p":"6097316393","t":"01","lat":40.1399,"lng":-74.465},{"n":"PEACEMAKER INDUSTRIES LLC","b":"","a":"322 WARWICK DRIVE","c":"CREAM RIDGE","s":"NJ","z":"08514","p":"7322213659","t":"07","lat":40.1399,"lng":-74.465},{"n":"SUNRISE ANTIQUES \u0026 AUCTIONEERS LLC","b":"","a":"79 OLD YORK RD","c":"CHESTERFIELD","s":"NJ","z":"08515","p":"8886394443","t":"01","lat":40.1151,"lng":-74.6393},{"n":"SCHWARTZKOPF, ROBERT","b":"BOB\u0027S SHOOTING SUPPLIES","a":"863 GROVE ST","c":"FLORENCE","s":"NJ","z":"08518","p":"6094990787","t":"01","lat":40.118,"lng":-74.8055},{"n":"LEFTARM LLC","b":"","a":"640 ETRA ROAD","c":"EAST WINDSOR","s":"NJ","z":"08520","p":"6094772016","t":"01","lat":40.2669,"lng":-74.525},{"n":"DEFENSIVE SECURITY LLC","b":"","a":"9 DEBBIE LN","c":"E WINDSOR","s":"NJ","z":"08520","p":"6094431686","t":"01","lat":40.2669,"lng":-74.525},{"n":"PINELAND SPORTING GOOD STORE LLC","b":"","a":"959 W VETERANS HWY","c":"JACKSON","s":"NJ","z":"08527","p":"7329617248","t":"01","lat":40.121,"lng":-74.3017},{"n":"PINELAND SPORTING GOOD STORE LLC","b":"","a":"959 WEST VETERANS HIGHWAY","c":"JACKSON","s":"NJ","z":"08527","p":"7329617248","t":"07","lat":40.121,"lng":-74.3017},{"n":"WRIGHT, JOSEPH R","b":"","a":"1218 RT 179","c":"LAMBERTVILLE","s":"NJ","z":"08530","p":"6093971285","t":"07","lat":40.3731,"lng":-74.9266},{"n":"SUPERANT ARMS, LLC","b":"","a":"6 STEEPLE VIEW CT","c":"LAMBERTVILLE","s":"NJ","z":"08530","p":"9083991328","t":"07","lat":40.3731,"lng":-74.9266},{"n":"BOAN, ROBERT WAYNE","b":"BOANS MARINE","a":"1296 ROUTE 179","c":"LAMBERTVILLE","s":"NJ","z":"08530","p":"6093973311","t":"01","lat":40.3731,"lng":-74.9266},{"n":"BOHONYI CORPORATION","b":"ANIMALS \u0026 GARDENS UNLIMITED","a":"14 JACOBSTOWN RD","c":"NEW EGYPT","s":"NJ","z":"08533","p":"6097520000","t":"01","lat":40.0713,"lng":-74.5067},{"n":"SHEEPDOG ARMS LLC","b":"","a":"212 ARCHERTOWN RD","c":"NEW EGYPT","s":"NJ","z":"08533","p":"6094106482","t":"01","lat":40.0713,"lng":-74.5067},{"n":"STRAIGHT SHOOTER ARMORY LLC","b":"","a":"108 INGLESIDE AVE","c":"PENNINGTON","s":"NJ","z":"08534","p":"6092405004","t":"01","lat":40.3339,"lng":-74.7944},{"n":"VANDERBECK, FRANK L","b":"CIRCLE X ARCHERY SUPPLY","a":"17 ROBERTS RD","c":"MILLSTONE TWP","s":"NJ","z":"08535","p":"7324468558","t":"01","lat":40.2739,"lng":-74.7162},{"n":"FIRST CLASS ENDEAVORS LLC","b":"","a":"700 STATE HIGHWAY ROUTE 33","c":"MILLSTONE TWP","s":"NJ","z":"08535","p":"7327866065","t":"01","lat":40.2739,"lng":-74.7162},{"n":"CLAY TARGET SPORTS INC","b":"","a":"339 COLD SOIL RD","c":"PRINCETON","s":"NJ","z":"08540","p":"6099219358","t":"01","lat":40.3666,"lng":-74.6408},{"n":"HEADQUARTERS ENTERPRIZES LLC","b":"HEADQUARTERS SHOOTING SUPPLY \u0026 GUNSMITHING","a":"231 RINGOES ROSEMONT RD","c":"STOCKTON","s":"NJ","z":"08559","p":"6095290126","t":"01","lat":40.4397,"lng":-74.9554},{"n":"SKIPS OUTDOORS LLC","b":"","a":"8 RISLER ST","c":"STOCKTON","s":"NJ","z":"08559","p":"6097736959","t":"01","lat":40.4397,"lng":-74.9554},{"n":"SURFACE TECHNOLOGY INC","b":"","a":"1405 LOWER FERRY RD","c":"EWING","s":"NJ","z":"08618","p":"6092590099","t":"07","lat":40.2377,"lng":-74.7821},{"n":"BOGART, DARRYL","b":"","a":"37 BURNSIDE AVENUE","c":"YARDVILLE","s":"NJ","z":"08620","p":"6098652209","t":"01","lat":40.167,"lng":-74.6488},{"n":"CAL III ENTERPRISES LLC","b":"","a":"2140 PENNINGTON RD","c":"EWING","s":"NJ","z":"08638","p":"6098833729","t":"01","lat":40.251,"lng":-74.7627},{"n":"KULAK ARMS \u0026 OUTFITTERS LLC","b":"","a":"415 LAWRENCE RD","c":"LAWRENCEVILLE","s":"NJ","z":"08648","p":"6096951043","t":"01","lat":40.2171,"lng":-74.7429},{"n":"PARABELLUM SPORTING GOODS LLC","b":"WESHOOT","a":"1955 SWARTHMORE AVE SUITE 5","c":"LAKEWOOD","s":"NJ","z":"08701","p":"7329876990","t":"01","lat":40.085,"lng":-74.2042},{"n":"FAIRBANKS, MARSHALL JR \u0026 PATRICIA","b":"A \u0026 M ARCHERY SUPPLY CO","a":"201 SECOND ST","c":"LAKEWOOD","s":"NJ","z":"08701","p":"7323632802","t":"01","lat":40.085,"lng":-74.2042},{"n":"SHORE SHOT PISTOL RANGE, INC","b":"","a":"730 AIRPORT ROAD","c":"LAKEWOOD","s":"NJ","z":"08701","p":"7329056888","t":"07","lat":40.085,"lng":-74.2042},{"n":"PARABELLUM SPORTING GOODS LLC","b":"WESHOOT","a":"1955 SWARTHMORE AVE, STE 5","c":"LAKEWOOD","s":"NJ","z":"08701","p":"7329876990","t":"07","lat":40.085,"lng":-74.2042},{"n":"LAND AND SEA SPORTS, LLC","b":"","a":"281 PRINCETON AVENUE","c":"BAYVILLE","s":"NJ","z":"08721","p":"7326740998","t":"01","lat":39.9093,"lng":-74.1549},{"n":"MLS ENTERPRISES UNLIMITED LLC","b":"ONE SHOT GUN SHOP","a":"782 ATLANTIC CITY BLVD","c":"BAYVILLE","s":"NJ","z":"08721","p":"7327880772","t":"07","lat":39.9093,"lng":-74.1549},{"n":"TRINITY CONSULTING NJ LLC","b":"TACTICAL CONCEPTS NJ","a":"7 FEDORNAK FREEWAY, UNITS 5 + 10 COMBINED","c":"BAYVILLE","s":"NJ","z":"08721","p":"7325527766","t":"07","lat":39.9093,"lng":-74.1549},{"n":"AMENDMENT 2 ARMORY LLC","b":"","a":"510 RTE 9, UNIT 5","c":"BAYVILLE","s":"NJ","z":"08721","p":"7326668818","t":"07","lat":39.9093,"lng":-74.1549},{"n":"MOREY, GERARD J SR","b":"GJ ARMS","a":"102 E SERPENTINE DR","c":"BAYVILLE","s":"NJ","z":"08721","p":"7326745031","t":"01","lat":39.9093,"lng":-74.1549},{"n":"RUTKOWSKI, RICHARD J \u0026 ABELLO, ANTHONY JR","b":"R\u0026M SECURITIES \u0026 FIREARMS, AMMO","a":"825 OCEAN AVE","c":"BEACHWOOD","s":"NJ","z":"08722","p":"7324739541","t":"01","lat":39.9302,"lng":-74.1961},{"n":"FREEDOM FIREARMS UNLIMITED LLC","b":"","a":"1800 DOUBLE TROUBLE ROAD","c":"BEACHWOOD","s":"NJ","z":"08722","p":"8482387172","t":"01","lat":39.9302,"lng":-74.1961},{"n":"FREEDOM FIREARMS UNLIMITED LLC","b":"","a":"1800 DOUBLE TROUBLE ROAD","c":"BEACHWOOD","s":"NJ","z":"08722","p":"8482387172","t":"08","lat":39.9302,"lng":-74.1961},{"n":"VICARI\u0027S GUN SALES LLC","b":"","a":"249 BRICK BLVD","c":"BRICK","s":"NJ","z":"08723","p":"7325044977","t":"01","lat":40.0389,"lng":-74.1109},{"n":"DINKLAGE, STEPHEN D","b":"FAMILY FIRE POWER","a":"7 POST ROAD","c":"BRICK","s":"NJ","z":"08724","p":"7329656710","t":"01","lat":40.0874,"lng":-74.1152},{"n":"SECUR-ALL FIREARMS LLC","b":"","a":"206 WASHINGTON DR","c":"BRICK","s":"NJ","z":"08724","p":"7328923113","t":"01","lat":40.0874,"lng":-74.1152},{"n":"FANIZZO, MICHAEL J DC","b":"AMERICAN ANTIQUES \u0026 SPORTING ARMS","a":"206 WASHINGTON DR","c":"BRICK","s":"NJ","z":"08724","p":"7322454804","t":"01","lat":40.0874,"lng":-74.1152},{"n":"STANDARD ARMS LLC","b":"","a":"127 TRUMAN DR","c":"BRICK","s":"NJ","z":"08724","p":"7326166603","t":"01","lat":40.0874,"lng":-74.1152},{"n":"STANDARD ARMS LLC","b":"","a":"127 TRUMAN DR","c":"BRICK","s":"NJ","z":"08724","p":"7326166603","t":"07","lat":40.0874,"lng":-74.1152},{"n":"JERSEY SPORTSMAN LLC","b":"","a":"1504 BEACH BLVD","c":"FORKED RIVER","s":"NJ","z":"08731","p":"6097564322","t":"01","lat":39.8444,"lng":-74.1973},{"n":"TRINITY ARMAMENT LLC","b":"","a":"1749 LAKESIDE DRIVE SOUTH","c":"FORKED RIVER","s":"NJ","z":"08731","p":"7187647716","t":"01","lat":39.8444,"lng":-74.1973},{"n":"GYGER, DIANA","b":"BAMBER ARMS DISTRIBUTORS","a":"1906 LACEY RD","c":"FORKED RIVER","s":"NJ","z":"08731","p":"6096931805","t":"01","lat":39.8444,"lng":-74.1973},{"n":"JWSERVICES LLC","b":"","a":"100 CAPTAIN GIGLIO WAY","c":"FORKED RIVER","s":"NJ","z":"08731","p":"6095480783","t":"07","lat":39.8444,"lng":-74.1973},{"n":"TRINITY ARMAMENT LLC","b":"","a":"1749 LAKESIDE DRIVE SOUTH","c":"FORKED RIVER","s":"NJ","z":"08731","p":"7187647716","t":"07","lat":39.8444,"lng":-74.1973},{"n":"TEAHAN, JOHN J","b":"JT CUSTOM GUNS \u0026 COLLECTABLES","a":"554 OAK HOLLOW LN","c":"LANOKA HARBOR","s":"NJ","z":"08734","p":"6097091346","t":"01","lat":39.862,"lng":-74.1668},{"n":"TOMS RIVER ARMORY INC","b":"","a":"602 CLIFTON AVE","c":"TOMS RIVER","s":"NJ","z":"08753","p":"7325693730","t":"01","lat":39.9771,"lng":-74.1565},{"n":"GUNS \u0026 ROSES LLC","b":"","a":"1521 RTE 37 WEST","c":"TOMS RIVER","s":"NJ","z":"08755","p":"7324076500","t":"01","lat":39.9999,"lng":-74.2228},{"n":"ELITE FIREARMS LLC","b":"","a":"2277 HUCKLEBERRY RD","c":"MANCHESTER","s":"NJ","z":"08759","p":"7326001604","t":"01","lat":39.9515,"lng":-74.1521},{"n":"CALMSTEEL ARMS LLC","b":"","a":"71 BEAVER AVENUE","c":"ANNANDALE","s":"NJ","z":"08801","p":"9088944344","t":"07","lat":40.6287,"lng":-74.8855},{"n":"WYANT, DANIEL JR","b":"DANS TAXIDERMY STUDIO","a":"1997 ROUTE 31N","c":"CLINTON","s":"NJ","z":"08809","p":"9086388909","t":"01","lat":40.6412,"lng":-74.9088},{"n":"THE K STREET GROUP, LLC","b":"","a":"12 LOWER CENTER STREET, SUITE 8, THE PARRY HOUSE","c":"CLINTON","s":"NJ","z":"08809","p":"9082007344","t":"01","lat":40.6412,"lng":-74.9088},{"n":"MIDDLEBROOK FIREARMS LLC","b":"","a":"288 HWY 22 WEST","c":"GREEN BROOK","s":"NJ","z":"08812","p":"7325296897","t":"01","lat":40.5897,"lng":-74.4639},{"n":"RARITAN RIVER CONSULTANTS, LLC","b":"","a":"59 PLAYER AVE","c":"EDISON","s":"NJ","z":"08817","p":"7328415426","t":"07","lat":40.5171,"lng":-74.3973},{"n":"WORLD CLASS STEEL LLC","b":"","a":"680 GROVE AVE","c":"EDISON","s":"NJ","z":"08820","p":"7324940274","t":"01","lat":40.578,"lng":-74.3589},{"n":"TACTICAL TRAINING CENTER LLC","b":"TTC LLC","a":"10A MINNEAKONING RD","c":"FLEMINGTON","s":"NJ","z":"08822","p":"9087829000","t":"01","lat":40.518,"lng":-74.8453},{"n":"ROTHMAN, HOWARD V","b":"","a":"16 FORRESTAL RD","c":"KENDALL PARK","s":"NJ","z":"08824","p":"7328215219","t":"01","lat":40.4208,"lng":-74.5529},{"n":"GUNWORKS LLC","b":"","a":"43 HORSESHOE BEND RD","c":"FRENCHTOWN","s":"NJ","z":"08825","p":"9084320349","t":"07","lat":40.5208,"lng":-75.0325},{"n":"MANNING, BRYAN TODD","b":"","a":"271 CR 513","c":"GLEN GARDNER","s":"NJ","z":"08826","p":"9082460911","t":"01","lat":40.7134,"lng":-74.9162},{"n":"MANNING, BRYAN TODD","b":"","a":"271 COUNTY ROAD 513","c":"GLEN GARDNER","s":"NJ","z":"08826","p":"9082460911","t":"07","lat":40.7134,"lng":-74.9162},{"n":"BILICKI, WALTER J JR","b":"DISCOUNT SPORTS","a":"20 SPRUCE RUN RD","c":"GLEN GARDNER","s":"NJ","z":"08826","p":"9085377235","t":"01","lat":40.7134,"lng":-74.9162},{"n":"FLYNN, JAMES C","b":"JIM FLYNNS TRUCK REPAIR","a":"2149 ROUTE 31","c":"GLEN GARDNER","s":"NJ","z":"08826","p":"9085376446","t":"01","lat":40.7134,"lng":-74.9162},{"n":"WOODBRIDGE ARMS COMPANY LLC","b":"","a":"23 QUEEN RD","c":"ISELIN","s":"NJ","z":"08830","p":"7328555887","t":"01","lat":40.5716,"lng":-74.3167},{"n":"ROC TRAINING LLC","b":"","a":"8 UNION HILL ROAD","c":"MONROE TOWNSHIP","s":"NJ","z":"08831","p":"9174453781","t":"01","lat":40.3192,"lng":-74.4285},{"n":"UNION HILL GUN CLUB LLC","b":"","a":"8 UNION HILL RD","c":"MONROE TWP","s":"NJ","z":"08831","p":"7328512044","t":"01","lat":40.3192,"lng":-74.4285},{"n":"AMERICAN SCOUT INC","b":"","a":"9 DAVISON AVENUE, SUITE #3","c":"JAMESBURG","s":"NJ","z":"08831","p":"6096387951","t":"07","lat":40.3192,"lng":-74.4285},{"n":"SC ARMS LLC","b":"","a":"36 W RAIL ROAD AVE","c":"JAMESBURG","s":"NJ","z":"08831","p":"7324254996","t":"07","lat":40.3192,"lng":-74.4285},{"n":"SC ARMS LLC","b":"","a":"36 W RAIL ROAD AVE","c":"JAMESBURG","s":"NJ","z":"08831","p":"7324254996","t":"08","lat":40.3192,"lng":-74.4285},{"n":"ZELASKO, GEORGE JR","b":"GEORGES SPORT SHOP","a":"51 E RAILROAD AVE  SUITE B","c":"JAMESBURG","s":"NJ","z":"08831","p":"7326560430","t":"01","lat":40.3192,"lng":-74.4285},{"n":"FASTFIRE ARMS LLC","b":"","a":"1221 ROUTE 22 EAST UNIT 1","c":"LEBANON","s":"NJ","z":"08833","p":"9082369000","t":"07","lat":40.6466,"lng":-74.829},{"n":"CHEYENNE GUNSMITH AND FIREARMS LLC","b":"","a":"834 LINCOLN AVE","c":"MANVILLE","s":"NJ","z":"08835","p":"9087254207","t":"01","lat":40.5399,"lng":-74.5934},{"n":"WALTER ARMS LLC","b":"","a":"101 LIBERTY ST","c":"METUCHEN","s":"NJ","z":"08840","p":"7325492187","t":"07","lat":40.5449,"lng":-74.3517},{"n":"LAGRUA, DENNIS ANTHONY","b":"FIREARMS SPECIALTIES","a":"354 ZION RD","c":"HILLSBOROUGH","s":"NJ","z":"08844","p":"9083697034","t":"01","lat":40.4775,"lng":-74.6272},{"n":"GIARRETTA, JOHN R","b":"J G FIREARMS","a":"813 LINCOLN BLVD","c":"MIDDLESEX","s":"NJ","z":"08846","p":"7322718991","t":"01","lat":40.5759,"lng":-74.5008},{"n":"DESAPIO, SANDRA","b":"RIVERSIDE ROD \u0026 GUN","a":"780 FRENCHTOWN","c":"MILFORD","s":"NJ","z":"08848","p":"9089634001","t":"01","lat":40.5929,"lng":-75.1025},{"n":"PELLECCHIA, PELLEGRINO J","b":"PELLECCHIA SPORTING ARMS CO","a":"439 COUNTY RD 579","c":"MILFORD","s":"NJ","z":"08848","p":"7325393141","t":"01","lat":40.5929,"lng":-75.1025},{"n":"QUALITY CASTING INC","b":"TAKE AIM ENGRAVING","a":"3310 BORDENTOWN AVENUE","c":"OLD BRIDGE","s":"NJ","z":"08857","p":"2123912962","t":"07","lat":40.398,"lng":-74.3236},{"n":"TECH OPS INTERNATIONAL CORPORATION","b":"","a":"110 SOUTH 5TH STREET","c":"PHILLIPSBURG","s":"NJ","z":"08865","p":"9084546030","t":"07","lat":40.7079,"lng":-75.1507},{"n":"JIMS SPORT CENTER INC","b":"THE OWLS NEST GUN \u0026 BOW","a":"97 RT 519","c":"PHILLIPSBURG","s":"NJ","z":"08865","p":"9089957903","t":"01","lat":40.7079,"lng":-75.1507},{"n":"LOU\u0027S GUN SHOP, INC","b":"","a":"91 WEST SOMERSET STREET","c":"RARITAN","s":"NJ","z":"08869","p":"9087255251","t":"07","lat":40.5711,"lng":-74.6377},{"n":"KOSMO, JOSEPH F","b":"SAYREVILLE SPORTSMAN","a":"52 WASHINGTON RD","c":"SAYREVILLE","s":"NJ","z":"08872","p":"7322382060","t":"01","lat":40.46,"lng":-74.3478},{"n":"DARK ARMS ENTERPRISE LLC","b":"","a":"223 HAWORTH PLACE","c":"SOMERSET","s":"NJ","z":"08873","p":"7324127036","t":"01","lat":40.5007,"lng":-74.5013},{"n":"CP TACTICAL LLC","b":"","a":"13 BARTLE RD","c":"SOMERSET","s":"NJ","z":"08873","p":"6466394838","t":"01","lat":40.5007,"lng":-74.5013},{"n":"ULTIMATE TRAINING MUNITIONS INC","b":"","a":"55 READINGTON RD","c":"NORTH BRANCH","s":"NJ","z":"08876","p":"9087259000","t":"01","lat":40.588,"lng":-74.6874},{"n":"HIGH CALIBER ORDNANCE LLC","b":"","a":"131 NORTH GASTON AVE UNIT 3","c":"SOMERVILLE","s":"NJ","z":"08876","p":"9089472360","t":"01","lat":40.588,"lng":-74.6874},{"n":"HERITAGE GUILD OF BRANCHBURG LLC","b":"","a":"3321 HWY 22 EAST","c":"BRANCHBURG","s":"NJ","z":"08876","p":"9084299500","t":"01","lat":40.588,"lng":-74.6874},{"n":"ULTIMATE TRAINING MUNITIONS INC","b":"","a":"55 READINGTON RD","c":"NORTH BRANCH","s":"NJ","z":"08876","p":"9087259000","t":"08","lat":40.588,"lng":-74.6874},{"n":"SC ARMS LLC","b":"","a":"210 SUMMERHILL RD UNIT #5","c":"SPOTSWOOD","s":"NJ","z":"08884","p":"7324254996","t":"01","lat":40.3847,"lng":-74.3894},{"n":"SC ARMS LLC","b":"","a":"210 SUMMERHILL RD SUITE 5","c":"SPOTSWOOD","s":"NJ","z":"08884","p":"7324254996","t":"07","lat":40.3847,"lng":-74.3894},{"n":"IMPACT DYNAMIC LLC","b":"SKY ARMORY","a":"510 GEORGES ROAD","c":"NORTH BRUNSWICK","s":"NJ","z":"08902","p":"7329554055","t":"07","lat":40.4538,"lng":-74.4823},{"n":"CENTURY 20 LLC","b":"","a":"72 RARITAN AVE","c":"HIGHLAND PARK","s":"NJ","z":"08904","p":"7322491345","t":"01","lat":40.4991,"lng":-74.4266}]